litebase/__init__.py
litebase/cli.py
litebase-0.0.4.dist-info/METADATA
litebase-0.0.4.dist-info/WHEEL
litebase-0.0.4.dist-info/entry_points.txt
litebase-0.0.4.dist-info/top_level.txt
litebase-0.0.4.dist-info/RECORD
